README.md
setup.py
nbunicorn/__init__.py
nbunicorn.egg-info/PKG-INFO
nbunicorn.egg-info/SOURCES.txt
nbunicorn.egg-info/dependency_links.txt
nbunicorn.egg-info/top_level.txt