Metadata-Version: 2.1
Name: nbunicorn
Version: 0.1
Summary: nbunicorn
Home-page: https://github.com/nbunicorn/nbunicorn
Author: Blair Hudson
Author-email: blair@nbunicorn.com
License: MIT
Keywords: data,machine,learning,science,algorithm,notebook
Platform: UNKNOWN
Classifier: Programming Language :: Python :: 3
Classifier: License :: OSI Approved :: MIT License
Classifier: Operating System :: OS Independent
